odoo/addons/l10n_th_account_tax_expense/README.rst
odoo/addons/l10n_th_account_tax_expense/__init__.py
odoo/addons/l10n_th_account_tax_expense/__manifest__.py
odoo/addons/l10n_th_account_tax_expense/i18n/l10n_th_account_tax_expense.pot
odoo/addons/l10n_th_account_tax_expense/models/__init__.py
odoo/addons/l10n_th_account_tax_expense/models/account_move.py
odoo/addons/l10n_th_account_tax_expense/models/hr_expense.py
odoo/addons/l10n_th_account_tax_expense/models/hr_expense_sheet.py
odoo/addons/l10n_th_account_tax_expense/readme/CONTRIBUTORS.rst
odoo/addons/l10n_th_account_tax_expense/readme/DESCRIPTION.rst
odoo/addons/l10n_th_account_tax_expense/static/description/icon.png
odoo/addons/l10n_th_account_tax_expense/static/description/index.html
odoo/addons/l10n_th_account_tax_expense/tests/__init__.py
odoo/addons/l10n_th_account_tax_expense/tests/test_expense_tax_invoice.py
odoo/addons/l10n_th_account_tax_expense/tests/test_expense_withholding_tax.py
odoo/addons/l10n_th_account_tax_expense/views/hr_expense_view.xml
odoo/addons/l10n_th_account_tax_expense/wizard/__init__.py
odoo/addons/l10n_th_account_tax_expense/wizard/account_payment_register.py
odoo/addons/l10n_th_account_tax_expense/wizard/account_payment_register_views.xml
odoo_addon_l10n_th_account_tax_expense-16.0.1.0.0.2.dist-info/METADATA
odoo_addon_l10n_th_account_tax_expense-16.0.1.0.0.2.dist-info/WHEEL
odoo_addon_l10n_th_account_tax_expense-16.0.1.0.0.2.dist-info/top_level.txt
odoo_addon_l10n_th_account_tax_expense-16.0.1.0.0.2.dist-info/RECORD
