Metadata-Version: 2.1
Name: odoo-addon-l10n_th_account_tax_expense
Version: 16.0.1.0.0.2
Summary: Thai Localization - Expense Tax
Home-page: https://github.com/OCA/l10n-thailand
Author: Ecosoft, Odoo Community Association (OCA)
Author-email: support@odoo-community.org
License: AGPL-3
Classifier: Programming Language :: Python
Classifier: Framework :: Odoo
Classifier: Framework :: Odoo :: 16.0
Classifier: License :: OSI Approved :: GNU Affero General Public License v3
Classifier: Development Status :: 4 - Beta
Requires-Python: >=3.10
Requires-Dist: odoo-addon-hr-expense-advance-clearing<16.1dev,>=16.0dev
Requires-Dist: odoo-addon-l10n-th-account-tax<16.1dev,>=16.0dev
Requires-Dist: odoo<16.1dev,>=16.0a
